searchalg/__init__.py
searchalg/algorithm.py
searchalg/node.py
searchalg/state.py
searchalg-0.0.2.dist-info/LICENSE
searchalg-0.0.2.dist-info/WHEEL
searchalg-0.0.2.dist-info/METADATA
searchalg-0.0.2.dist-info/RECORD
