Metadata-Version: 2.1
Name: searchalg
Version: 0.0.2
Summary: A package for search optimization algorithms.
Author-email: Hatchi Kiqo <hatchikiqo@gmail.com>
Requires-Python: >=3.7
Classifier: License :: OSI Approved :: MIT License
Requires-Dist: loguru >= 0.5.3
Requires-Dist: pytest ; extra == "test"
Requires-Dist: pytest-cov ; extra == "test"
Provides-Extra: test
